mt
test
