Metadata-Version: 1.0
Name: Museu
Version: 2.4
Summary: 常用工具包
Home-page: https://github.com/Blackstone1204
Author: blackstone
Author-email: 971406187@qq.com
License: UNKNOWN
Platform: UNKNOWN
